strax/__init__.py
strax/chunk.py
strax/config.py
strax/context.py
strax/dtypes.py
strax/io.py
strax/mailbox.py
strax/plugins/__init__.py
strax/plugins/cut_plugin.py
strax/plugins/down_chunking_plugin.py
strax/plugins/exhaust_plugin.py
strax/plugins/loop_plugin.py
strax/plugins/merge_only_plugin.py
strax/plugins/overlap_window_plugin.py
strax/plugins/parrallel_source_plugin.py
strax/plugins/plugin.py
strax/processing/__init__.py
strax/processing/data_reduction.py
strax/processing/general.py
strax/processing/hitlets.py
strax/processing/peak_building.py
strax/processing/peak_merging.py
strax/processing/peak_properties.py
strax/processing/peak_splitting.py
strax/processing/pulse_processing.py
strax/processing/statistics.py
strax/processor.py
strax/processors/__init__.py
strax/processors/base.py
strax/processors/post_office.py
strax/processors/single_thread.py
strax/processors/threaded_mailbox.py
strax/run_selection.py
strax/scripts/__init__.py
strax/scripts/rechunker.py
strax/sort_enforcement.py
strax/storage/__init__.py
strax/storage/common.py
strax/storage/file_rechunker.py
strax/storage/files.py
strax/storage/mongo.py
strax/storage/zipfiles.py
strax/testutils.py
strax/utils.py
strax-2.2.2.dist-info/METADATA
strax-2.2.2.dist-info/WHEEL
strax-2.2.2.dist-info/entry_points.txt
strax-2.2.2.dist-info/licenses/LICENSE
strax-2.2.2.dist-info/RECORD
