Metadata-Version: 2.4
Name: strax
Version: 2.2.2
Summary: Streaming analysis for xenon TPCs
License-File: LICENSE
Author: strax developers
Requires-Python: >=3.10,<3.13
Classifier: Development Status :: 5 - Production/Stable
Classifier: Intended Audience :: Science/Research
Classifier: License :: OSI Approved :: BSD License
Classifier: Natural Language :: English
Classifier: Programming Language :: Python :: 3
Classifier: Programming Language :: Python :: 3.10
Classifier: Programming Language :: Python :: 3.11
Classifier: Programming Language :: Python :: 3.12
Classifier: Programming Language :: Python :: Implementation :: CPython
Classifier: Topic :: Scientific/Engineering :: Physics
Provides-Extra: docs
Requires-Dist: blosc
Requires-Dist: click
Requires-Dist: deepdiff
Requires-Dist: dill
Requires-Dist: fsspec
Requires-Dist: graphviz ; extra == "docs"
Requires-Dist: immutabledict
Requires-Dist: lxml_html_clean ; extra == "docs"
Requires-Dist: lz4
Requires-Dist: m2r ; extra == "docs"
Requires-Dist: mistune (==0.8.4) ; extra == "docs"
Requires-Dist: nbsphinx ; extra == "docs"
Requires-Dist: numba (>=0.43.1)
Requires-Dist: numcodecs (<0.16.0)
Requires-Dist: numexpr
Requires-Dist: numpy (>=1.18.5)
Requires-Dist: packaging
Requires-Dist: pandas
Requires-Dist: psutil
Requires-Dist: pymongo
Requires-Dist: recommonmark ; extra == "docs"
Requires-Dist: scipy
Requires-Dist: sphinx ; extra == "docs"
Requires-Dist: sphinx_rtd_theme ; extra == "docs"
Requires-Dist: tqdm (>=4.46.0)
Requires-Dist: urllib3 (==2.2.2) ; extra == "docs"
Requires-Dist: zarr (<3.0.0)
Requires-Dist: zstandard
Requires-Dist: zstd
Project-URL: Repository, https://github.com/AxFoundation/strax
